pypdf2extractor/__init__.py
pypdf2extractor/pypdf2extractor.py
pypdf2extractor-0.2.0.dist-info/licenses/LICENSE
pypdf2extractor-0.2.0.dist-info/METADATA
pypdf2extractor-0.2.0.dist-info/WHEEL
pypdf2extractor-0.2.0.dist-info/entry_points.txt
pypdf2extractor-0.2.0.dist-info/top_level.txt
pypdf2extractor-0.2.0.dist-info/RECORD
