Metadata-Version: 2.4
Name: pypdf2extractor
Version: 0.2.0
Summary: A tool to extract text and tables from PDF files
Home-page: https://github.com/sathu08/pypdf2extractor
Author: SathyaPrakash
Author-email: sathiyaprakash881@gmail.com
License: MIT
Classifier: Programming Language :: Python :: 3
Classifier: License :: OSI Approved :: MIT License
Classifier: Operating System :: OS Independent
Requires-Python: >=3.10
License-File: LICENSE
Requires-Dist: opencv-python
Requires-Dist: numpy
Requires-Dist: pandas
Requires-Dist: pytesseract
Requires-Dist: pdf2image
Requires-Dist: tabulate
Dynamic: author
Dynamic: author-email
Dynamic: classifier
Dynamic: description
Dynamic: description-content-type
Dynamic: home-page
Dynamic: license
Dynamic: license-file
Dynamic: requires-dist
Dynamic: requires-python
Dynamic: summary
